{
    "recording": {
        "id": "a1315c6c-9a3c-4ae2-819d-63505727a24c",
        "title": "Maple Leaf Rag",
        "length": "175640",
        "artist-credit": [
            {
                "artist": {
                    "id": "8ad3d3e1-0a20-4fe3-8c50-38293f62638d",
                    "type": "Group",
                    "name": "New Orleans Feetwarmers",
                    "sort-name": "New Orleans Feetwarmers",
                    "alias-list": [
                        {
                            "sort-name": "The New Orleans Feetwarmers",
                            "alias": "The New Orleans Feetwarmers"
                        }
                    ],
                    "alias-count": 1
                }
            }
        ],
        "release-list": [
            {
                "id": "19af4fa3-ce3d-48f1-b81f-fd12b7405f1f",
                "title": "The Chronological Classics: Sidney Bechet 1923-1936",
                "status": "Official",
                "quality": "normal",
                "packaging": "Jewel Case",
                "text-representation": {
                    "language": "eng",
                    "script": "Latn"
                },
                "artist-credit": [
                    {
                        "artist": {
                            "id": "bf1b23ea-9b76-42cf-a5f6-4a691e81af5e",
                            "type": "Person",
                            "name": "Sidney Bechet",
                            "sort-name": "Bechet, Sidney"
                        }
                    }
                ],
                "date": "1991",
                "country": "FR",
                "release-event-list": [
                    {
                        "date": "1991",
                        "area": {
                            "id": "08310658-51eb-3801-80de-5a0739207115",
                            "name": "France",
                            "sort-name": "France",
                            "iso-3166-1-code-list": [
                                "FR"
                            ]
                        }
                    }
                ],
                "release-event-count": 1,
                "barcode": "3307517058324",
                "medium-list": [
                    {
                        "position": "1",
                        "format": "CD",
                        "disc-list": [],
                        "disc-count": 0,
                        "track-list": [
                            {
                                "id": "6a716d1d-b2b5-335a-bb2f-5beaf5dd2168",
                                "position": "13",
                                "number": "13",
                                "title": "Maple Leaf Rag",
                                "length": "175000",
                                "artist-credit": [
                                    {
                                        "artist": {
                                            "id": "8ad3d3e1-0a20-4fe3-8c50-38293f62638d",
                                            "type": "Group",
                                            "name": "New Orleans Feetwarmers",
                                            "sort-name": "New Orleans Feetwarmers",
                                            "alias-list": [
                                                {
                                                    "sort-name": "The New Orleans Feetwarmers",
                                                    "alias": "The New Orleans Feetwarmers"
                                                }
                                            ],
                                            "alias-count": 1
                                        }
                                    }
                                ],
                                "artist-credit-phrase": "New Orleans Feetwarmers",
                                "track_or_recording_length": "175000"
                            }
                        ],
                        "track-count": 24
                    }
                ],
                "medium-count": 1,
                "artist-credit-phrase": "Sidney Bechet"
            },
            {
                "id": "f2ec369f-ee55-464f-b5ef-f8abdb69cce8",
                "title": "Sidney Bechet, Volume 3: 1931-1937",
                "status": "Official",
                "quality": "normal",
                "packaging": "Jewel Case",
                "text-representation": {
                    "language": "eng",
                    "script": "Latn"
                },
                "artist-credit": [
                    {
                        "artist": {
                            "id": "bf1b23ea-9b76-42cf-a5f6-4a691e81af5e",
                            "type": "Person",
                            "name": "Sidney Bechet",
                            "sort-name": "Bechet, Sidney"
                        }
                    }
                ],
                "date": "1992",
                "release-event-list": [
                    {
                        "date": "1992"
                    }
                ],
                "release-event-count": 1,
                "barcode": "3356571002729",
                "medium-list": [
                    {
                        "position": "1",
                        "format": "CD",
                        "disc-list": [],
                        "disc-count": 0,
                        "track-list": [
                            {
                                "id": "d09286bc-043b-44c0-bfc8-f6b92c87cdd1",
                                "position": "10",
                                "number": "10",
                                "title": "Maple Leaf Rag",
                                "length": "176666",
                                "artist-credit": [
                                    {
                                        "artist": {
                                            "id": "8ad3d3e1-0a20-4fe3-8c50-38293f62638d",
                                            "type": "Group",
                                            "name": "New Orleans Feetwarmers",
                                            "sort-name": "New Orleans Feetwarmers",
                                            "alias-list": [
                                                {
                                                    "sort-name": "The New Orleans Feetwarmers",
                                                    "alias": "The New Orleans Feetwarmers"
                                                }
                                            ],
                                            "alias-count": 1
                                        }
                                    }
                                ],
                                "artist-credit-phrase": "New Orleans Feetwarmers",
                                "track_or_recording_length": "176666"
                            }
                        ],
                        "track-count": 22
                    }
                ],
                "medium-count": 1,
                "artist-credit-phrase": "Sidney Bechet"
            },
            {
                "id": "b476852c-a999-415a-82a8-4df34747e041",
                "title": "The Collection",
                "status": "Official",
                "quality": "normal",
                "packaging": "Jewel Case",
                "text-representation": {
                    "language": "eng",
                    "script": "Latn"
                },
                "artist-credit": [
                    {
                        "artist": {
                            "id": "bf1b23ea-9b76-42cf-a5f6-4a691e81af5e",
                            "type": "Person",
                            "name": "Sidney Bechet",
                            "sort-name": "Bechet, Sidney"
                        }
                    }
                ],
                "date": "1992",
                "country": "FR",
                "release-event-list": [
                    {
                        "date": "1992",
                        "area": {
                            "id": "08310658-51eb-3801-80de-5a0739207115",
                            "name": "France",
                            "sort-name": "France",
                            "iso-3166-1-code-list": [
                                "FR"
                            ]
                        }
                    }
                ],
                "release-event-count": 1,
                "barcode": "0035629068728",
                "medium-list": [
                    {
                        "position": "1",
                        "format": "CD",
                        "disc-list": [],
                        "disc-count": 0,
                        "track-list": [
                            {
                                "id": "b767a3d2-6459-3b1a-a363-70f378c007f8",
                                "position": "2",
                                "number": "2",
                                "title": "Maple Leaf Rag",
                                "length": "176000",
                                "artist-credit": [
                                    {
                                        "artist": {
                                            "id": "bf1b23ea-9b76-42cf-a5f6-4a691e81af5e",
                                            "type": "Person",
                                            "name": "Sidney Bechet",
                                            "sort-name": "Bechet, Sidney"
                                        }
                                    }
                                ],
                                "artist-credit-phrase": "Sidney Bechet",
                                "track_or_recording_length": "176000"
                            }
                        ],
                        "track-count": 20
                    }
                ],
                "medium-count": 1,
                "artist-credit-phrase": "Sidney Bechet"
            },
            {
                "id": "dc928be6-a7e9-4390-b2d9-e20f1deff60f",
                "title": "The Complete Sidney Bechet, Volumes 1/2 (1932\u20131941)",
                "status": "Official",
                "quality": "normal",
                "packaging": "Jewel Case",
                "text-representation": {
                    "language": "fra"
                },
                "artist-credit": [
                    {
                        "artist": {
                            "id": "bf1b23ea-9b76-42cf-a5f6-4a691e81af5e",
                            "type": "Person",
                            "name": "Sidney Bechet",
                            "sort-name": "Bechet, Sidney"
                        }
                    }
                ],
                "date": "1992",
                "release-event-list": [
                    {
                        "date": "1992"
                    }
                ],
                "release-event-count": 1,
                "barcode": "078636649825",
                "medium-list": [
                    {
                        "position": "1",
                        "format": "CD",
                        "disc-list": [
                            {
                                "id": "NAfvi.SIKnc6MLBTCTPdaqXz9ME-",
                                "sectors": "231337",
                                "offset-list": [
                                    187,
                                    12977,
                                    27012,
                                    41520,
                                    56175,
                                    69315,
                                    83362,
                                    96420,
                                    112820,
                                    125155,
                                    138947,
                                    153130,
                                    164350,
                                    178155,
                                    192667,
                                    206430,
                                    219347
                                ],
                                "offset-count": 17
                            }
                        ],
                        "disc-count": 1,
                        "track-list": [
                            {
                                "id": "08d879e9-75c3-4d77-b3b0-caceff3a7bf6",
                                "position": "5",
                                "number": "5",
                                "title": "Maple Leaf Rag",
                                "length": "175200",
                                "artist-credit": [
                                    {
                                        "artist": {
                                            "id": "bf1b23ea-9b76-42cf-a5f6-4a691e81af5e",
                                            "type": "Person",
                                            "name": "Sidney Bechet",
                                            "sort-name": "Bechet, Sidney"
                                        }
                                    }
                                ],
                                "artist-credit-phrase": "Sidney Bechet",
                                "track_or_recording_length": "175200"
                            }
                        ],
                        "track-count": 17
                    }
                ],
                "medium-count": 1,
                "artist-credit-phrase": "Sidney Bechet"
            },
            {
                "id": "6588e8dc-7213-4c92-8d7e-2cdf7715ccb4",
                "title": "The History of Jazz: New Orleans Joys",
                "status": "Official",
                "quality": "normal",
                "packaging": "Jewel Case",
                "text-representation": {
                    "language": "eng",
                    "script": "Latn"
                },
                "artist-credit": [
                    {
                        "artist": {
                            "id": "89ad4ac3-39f7-470e-963a-56509c546377",
                            "type": "Other",
                            "name": "Various Artists",
                            "sort-name": "Various Artists",
                            "disambiguation": "add compilations to this artist"
                        }
                    }
                ],
                "date": "1994",
                "country": "NL",
                "release-event-list": [
                    {
                        "date": "1994",
                        "area": {
                            "id": "ef1b7cc0-cd26-36f4-8ea0-04d9623786c7",
                            "name": "Netherlands",
                            "sort-name": "Netherlands",
                            "iso-3166-1-code-list": [
                                "NL"
                            ]
                        }
                    }
                ],
                "release-event-count": 1,
                "barcode": "8711539580018",
                "medium-list": [
                    {
                        "position": "2",
                        "format": "CD",
                        "disc-list": [
                            {
                                "id": "Dn4vwRdBSPMrcokSeE.49HsJvac-",
                                "sectors": "250427",
                                "offset-list": [
                                    150,
                                    14967,
                                    29140,
                                    41920,
                                    55322,
                                    70797,
                                    82967,
                                    95947,
                                    109267,
                                    122035,
                                    138505,
                                    151892,
                                    164620,
                                    178597,
                                    191192,
                                    205885,
                                    218940,
                                    232080
                                ],
                                "offset-count": 18
                            }
                        ],
                        "disc-count": 1,
                        "track-list": [
                            {
                                "id": "74ba1f0d-897c-3ccd-8970-df553316ce9e",
                                "position": "8",
                                "number": "8",
                                "title": "Maple Leaf Rag",
                                "length": "177600",
                                "artist-credit": [
                                    {
                                        "artist": {
                                            "id": "8ad3d3e1-0a20-4fe3-8c50-38293f62638d",
                                            "type": "Group",
                                            "name": "New Orleans Feetwarmers",
                                            "sort-name": "New Orleans Feetwarmers",
                                            "alias-list": [
                                                {
                                                    "sort-name": "The New Orleans Feetwarmers",
                                                    "alias": "The New Orleans Feetwarmers"
                                                }
                                            ],
                                            "alias-count": 1
                                        }
                                    }
                                ],
                                "artist-credit-phrase": "New Orleans Feetwarmers",
                                "track_or_recording_length": "177600"
                            }
                        ],
                        "track-count": 18
                    }
                ],
                "medium-count": 1,
                "artist-credit-phrase": "Various Artists"
            },
            {
                "id": "a99af9e8-a165-4420-9c04-e5cd828e4bcc",
                "title": "Summertime: 1932-1940",
                "status": "Official",
                "quality": "normal",
                "text-representation": {
                    "language": "eng",
                    "script": "Latn"
                },
                "artist-credit": [
                    {
                        "artist": {
                            "id": "bf1b23ea-9b76-42cf-a5f6-4a691e81af5e",
                            "type": "Person",
                            "name": "Sidney Bechet",
                            "sort-name": "Bechet, Sidney"
                        }
                    }
                ],
                "date": "1999",
                "release-event-list": [
                    {
                        "date": "1999"
                    }
                ],
                "release-event-count": 1,
                "medium-list": [
                    {
                        "position": "1",
                        "format": "CD",
                        "disc-list": [
                            {
                                "id": "A5rWFLj9rSucRqmIPwE3C8rPSWk-",
                                "sectors": "324890",
                                "offset-list": [
                                    150,
                                    14557,
                                    27235,
                                    41247,
                                    54337,
                                    70612,
                                    84155,
                                    98735,
                                    112627,
                                    125602,
                                    137802,
                                    152032,
                                    166325,
                                    178962,
                                    193090,
                                    204192,
                                    216610,
                                    230810,
                                    244920,
                                    259320,
                                    272177,
                                    283230,
                                    293922,
                                    306442
                                ],
                                "offset-count": 24
                            }
                        ],
                        "disc-count": 1,
                        "track-list": [
                            {
                                "id": "486e6a5a-c67b-3915-89c9-a18e70a4c3a2",
                                "position": "4",
                                "number": "4",
                                "title": "Maple Leaf Rag",
                                "length": "174000",
                                "artist-credit": [
                                    {
                                        "artist": {
                                            "id": "bf1b23ea-9b76-42cf-a5f6-4a691e81af5e",
                                            "type": "Person",
                                            "name": "Sidney Bechet",
                                            "sort-name": "Bechet, Sidney"
                                        }
                                    }
                                ],
                                "artist-credit-phrase": "Sidney Bechet",
                                "track_or_recording_length": "174000"
                            }
                        ],
                        "track-count": 24
                    }
                ],
                "medium-count": 1,
                "artist-credit-phrase": "Sidney Bechet"
            },
            {
                "id": "0671ecb8-e8a5-4ee2-a933-f73fc1c93a4a",
                "title": "Les Triomphes du jazz",
                "status": "Official",
                "quality": "normal",
                "text-representation": {
                    "language": "eng",
                    "script": "Latn"
                },
                "artist-credit": [
                    {
                        "artist": {
                            "id": "89ad4ac3-39f7-470e-963a-56509c546377",
                            "type": "Other",
                            "name": "Various Artists",
                            "sort-name": "Various Artists",
                            "disambiguation": "add compilations to this artist"
                        }
                    }
                ],
                "date": "2000",
                "country": "FR",
                "release-event-list": [
                    {
                        "date": "2000",
                        "area": {
                            "id": "08310658-51eb-3801-80de-5a0739207115",
                            "name": "France",
                            "sort-name": "France",
                            "iso-3166-1-code-list": [
                                "FR"
                            ]
                        }
                    }
                ],
                "release-event-count": 1,
                "barcode": "3565381112010",
                "medium-list": [
                    {
                        "title": "Sidney Bechet",
                        "position": "2",
                        "format": "CD",
                        "disc-list": [
                            {
                                "id": "Hi6zA8nAJo9zwWIEomEYuY4HsGI-",
                                "sectors": "336880",
                                "offset-list": [
                                    150,
                                    13655,
                                    26840,
                                    40805,
                                    53355,
                                    67770,
                                    78912,
                                    95137,
                                    108975,
                                    127685,
                                    138675,
                                    152787,
                                    167587,
                                    180850,
                                    192182,
                                    206467,
                                    220097,
                                    240157,
                                    256645,
                                    270007,
                                    282392,
                                    296565,
                                    310215,
                                    324775
                                ],
                                "offset-count": 24
                            }
                        ],
                        "disc-count": 1,
                        "track-list": [
                            {
                                "id": "c5c97d10-b508-3b52-a62c-963782d18e4c",
                                "position": "2",
                                "number": "2",
                                "title": "Maple Leaf Rag",
                                "length": "175800",
                                "artist-credit": [
                                    {
                                        "artist": {
                                            "id": "8ad3d3e1-0a20-4fe3-8c50-38293f62638d",
                                            "type": "Group",
                                            "name": "New Orleans Feetwarmers",
                                            "sort-name": "New Orleans Feetwarmers",
                                            "alias-list": [
                                                {
                                                    "sort-name": "The New Orleans Feetwarmers",
                                                    "alias": "The New Orleans Feetwarmers"
                                                }
                                            ],
                                            "alias-count": 1
                                        }
                                    }
                                ],
                                "artist-credit-phrase": "New Orleans Feetwarmers",
                                "track_or_recording_length": "175800"
                            }
                        ],
                        "track-count": 24
                    }
                ],
                "medium-count": 1,
                "artist-credit-phrase": "Various Artists"
            },
            {
                "id": "1d7abf66-8579-49cd-b454-00aaad34b153",
                "title": "The Sidney Bechet Story",
                "status": "Official",
                "quality": "normal",
                "text-representation": {
                    "language": "eng",
                    "script": "Latn"
                },
                "artist-credit": [
                    {
                        "artist": {
                            "id": "bf1b23ea-9b76-42cf-a5f6-4a691e81af5e",
                            "type": "Person",
                            "name": "Sidney Bechet",
                            "sort-name": "Bechet, Sidney"
                        }
                    }
                ],
                "date": "2001-02-19",
                "country": "GB",
                "release-event-list": [
                    {
                        "date": "2001-02-19",
                        "area": {
                            "id": "8a754a16-0027-3a29-b6d7-2b40ea0481ed",
                            "name": "United Kingdom",
                            "sort-name": "United Kingdom",
                            "iso-3166-1-code-list": [
                                "GB"
                            ]
                        }
                    }
                ],
                "release-event-count": 1,
                "barcode": "604988991826",
                "medium-list": [
                    {
                        "title": "Wild Cat Blues",
                        "position": "1",
                        "format": "CD",
                        "disc-list": [
                            {
                                "id": "f7yWjor8SpfbGof7E3N42JXZYSc-",
                                "sectors": "325792",
                                "offset-list": [
                                    150,
                                    13849,
                                    27316,
                                    40727,
                                    55286,
                                    69643,
                                    84325,
                                    97470,
                                    111030,
                                    124685,
                                    139727,
                                    152533,
                                    166597,
                                    181139,
                                    195805,
                                    209945,
                                    223118,
                                    235791,
                                    247056,
                                    260118,
                                    271776,
                                    285236,
                                    298829,
                                    311471
                                ],
                                "offset-count": 24
                            }
                        ],
                        "disc-count": 1,
                        "track-list": [
                            {
                                "id": "fa998588-b59a-304c-8b5d-ce8c14ec8a6d",
                                "position": "16",
                                "number": "16",
                                "title": "Maple Leaf Rag",
                                "length": "175640",
                                "artist-credit": [
                                    {
                                        "artist": {
                                            "id": "8ad3d3e1-0a20-4fe3-8c50-38293f62638d",
                                            "type": "Group",
                                            "name": "New Orleans Feetwarmers",
                                            "sort-name": "New Orleans Feetwarmers",
                                            "alias-list": [
                                                {
                                                    "sort-name": "The New Orleans Feetwarmers",
                                                    "alias": "The New Orleans Feetwarmers"
                                                }
                                            ],
                                            "alias-count": 1
                                        }
                                    }
                                ],
                                "artist-credit-phrase": "New Orleans Feetwarmers",
                                "track_or_recording_length": "175640"
                            }
                        ],
                        "track-count": 24
                    }
                ],
                "medium-count": 1,
                "tag-list": [
                    {
                        "count": "1",
                        "name": "jazz"
                    }
                ],
                "artist-credit-phrase": "Sidney Bechet"
            },
            {
                "id": "69b696d5-b85e-4ac5-8230-e12b79a77f72",
                "title": "Les 100 plus grands succ\u00e8s du Jazz New Orleans",
                "status": "Official",
                "quality": "normal",
                "packaging": "Jewel Case",
                "text-representation": {
                    "language": "eng",
                    "script": "Latn"
                },
                "artist-credit": [
                    {
                        "artist": {
                            "id": "89ad4ac3-39f7-470e-963a-56509c546377",
                            "type": "Other",
                            "name": "Various Artists",
                            "sort-name": "Various Artists",
                            "disambiguation": "add compilations to this artist"
                        }
                    }
                ],
                "date": "2002-04-23",
                "country": "FR",
                "release-event-list": [
                    {
                        "date": "2002-04-23",
                        "area": {
                            "id": "08310658-51eb-3801-80de-5a0739207115",
                            "name": "France",
                            "sort-name": "France",
                            "iso-3166-1-code-list": [
                                "FR"
                            ]
                        }
                    }
                ],
                "release-event-count": 1,
                "barcode": "724381229026",
                "medium-list": [
                    {
                        "position": "2",
                        "format": "CD",
                        "disc-list": [],
                        "disc-count": 0,
                        "track-list": [
                            {
                                "id": "942eaea4-25e3-4038-aa4f-55de29825208",
                                "position": "24",
                                "number": "24",
                                "title": "Maple Leaf Rag",
                                "length": "175000",
                                "artist-credit": [
                                    {
                                        "artist": {
                                            "id": "8ad3d3e1-0a20-4fe3-8c50-38293f62638d",
                                            "type": "Group",
                                            "name": "New Orleans Feetwarmers",
                                            "sort-name": "New Orleans Feetwarmers",
                                            "alias-list": [
                                                {
                                                    "sort-name": "The New Orleans Feetwarmers",
                                                    "alias": "The New Orleans Feetwarmers"
                                                }
                                            ],
                                            "alias-count": 1
                                        }
                                    }
                                ],
                                "artist-credit-phrase": "New Orleans Feetwarmers",
                                "track_or_recording_length": "175000"
                            }
                        ],
                        "track-count": 26
                    }
                ],
                "medium-count": 1,
                "artist-credit-phrase": "Various Artists"
            },
            {
                "id": "a13a970e-e51f-4f7d-8d7c-757ce782f420",
                "title": "Jazz Legends",
                "status": "Official",
                "quality": "normal",
                "packaging": "Jewel Case",
                "text-representation": {
                    "language": "eng",
                    "script": "Latn"
                },
                "artist-credit": [
                    {
                        "artist": {
                            "id": "89ad4ac3-39f7-470e-963a-56509c546377",
                            "type": "Other",
                            "name": "Various Artists",
                            "sort-name": "Various Artists",
                            "disambiguation": "add compilations to this artist"
                        }
                    }
                ],
                "date": "2002",
                "country": "GB",
                "release-event-list": [
                    {
                        "date": "2002",
                        "area": {
                            "id": "8a754a16-0027-3a29-b6d7-2b40ea0481ed",
                            "name": "United Kingdom",
                            "sort-name": "United Kingdom",
                            "iso-3166-1-code-list": [
                                "GB"
                            ]
                        }
                    }
                ],
                "release-event-count": 1,
                "barcode": "698458151124",
                "medium-list": [
                    {
                        "position": "1",
                        "format": "CD",
                        "disc-list": [
                            {
                                "id": "ZY26haCAbUFq37_z2URGFVENPRg-",
                                "sectors": "274724",
                                "offset-list": [
                                    150,
                                    14828,
                                    25276,
                                    38637,
                                    52556,
                                    65953,
                                    79981,
                                    92335,
                                    106596,
                                    121223,
                                    135219,
                                    150000,
                                    161369,
                                    175318,
                                    195630,
                                    205945,
                                    218699,
                                    232121,
                                    245896,
                                    259237
                                ],
                                "offset-count": 20
                            }
                        ],
                        "disc-count": 1,
                        "track-list": [
                            {
                                "id": "18837049-a063-31ef-a3b7-b18b9dbe1fe3",
                                "position": "17",
                                "number": "17",
                                "title": "Maple Leaf Rag",
                                "length": "179000",
                                "artist-credit": [
                                    {
                                        "artist": {
                                            "id": "bf1b23ea-9b76-42cf-a5f6-4a691e81af5e",
                                            "type": "Person",
                                            "name": "Sidney Bechet",
                                            "sort-name": "Bechet, Sidney"
                                        }
                                    }
                                ],
                                "artist-credit-phrase": "Sidney Bechet",
                                "track_or_recording_length": "179000"
                            }
                        ],
                        "track-count": 20
                    }
                ],
                "medium-count": 1,
                "artist-credit-phrase": "Various Artists"
            },
            {
                "id": "24e0963d-0714-4bca-91b1-8b1aa4946ece",
                "title": "The Ultimate Jazz Archive",
                "status": "Official",
                "quality": "normal",
                "packaging": "Keep Case",
                "text-representation": {
                    "language": "eng",
                    "script": "Latn"
                },
                "artist-credit": [
                    {
                        "artist": {
                            "id": "89ad4ac3-39f7-470e-963a-56509c546377",
                            "type": "Other",
                            "name": "Various Artists",
                            "sort-name": "Various Artists",
                            "disambiguation": "add compilations to this artist"
                        }
                    }
                ],
                "date": "2005-08-29",
                "country": "DE",
                "release-event-list": [
                    {
                        "date": "2005-08-29",
                        "area": {
                            "id": "85752fda-13c4-31a3-bee5-0e5cb1f51dad",
                            "name": "Germany",
                            "sort-name": "Germany",
                            "iso-3166-1-code-list": [
                                "DE"
                            ]
                        }
                    }
                ],
                "release-event-count": 1,
                "barcode": "4011222228000",
                "medium-list": [
                    {
                        "title": "Classic Jazz, Ragtime, Dixieland \u2013 Sidney Bechet",
                        "position": "21",
                        "format": "CD",
                        "disc-list": [],
                        "disc-count": 0,
                        "track-list": [
                            {
                                "id": "3e986b75-eebb-327d-93fc-a8287768d805",
                                "position": "4",
                                "number": "4",
                                "title": "Maple Leaf Rag",
                                "length": "175106",
                                "artist-credit": [
                                    {
                                        "artist": {
                                            "id": "bf1b23ea-9b76-42cf-a5f6-4a691e81af5e",
                                            "type": "Person",
                                            "name": "Sidney Bechet",
                                            "sort-name": "Bechet, Sidney"
                                        }
                                    }
                                ],
                                "artist-credit-phrase": "Sidney Bechet",
                                "track_or_recording_length": "175106"
                            }
                        ],
                        "track-count": 20
                    }
                ],
                "medium-count": 1,
                "artist-credit-phrase": "Various Artists"
            },
            {
                "id": "3b698204-6d4b-4dd1-b0a7-1cd0c0b1f08f",
                "title": "The Ultimate Jazz Archive, Set 06: Classic Jazz, Ragtime, Dixieland",
                "status": "Official",
                "quality": "normal",
                "text-representation": {
                    "language": "eng",
                    "script": "Latn"
                },
                "artist-credit": [
                    {
                        "artist": {
                            "id": "bf1b23ea-9b76-42cf-a5f6-4a691e81af5e",
                            "type": "Person",
                            "name": "Sidney Bechet",
                            "sort-name": "Bechet, Sidney"
                        }
                    },
                    ", ",
                    {
                        "artist": {
                            "id": "fef8ae6b-b1c9-4412-a627-1958ea222289",
                            "type": "Group",
                            "name": "Washboard Rhythm Kings",
                            "sort-name": "Washboard Rhythm Kings"
                        }
                    },
                    ", ",
                    {
                        "artist": {
                            "id": "a3aea435-d1fb-45ca-b38d-411335d4717f",
                            "type": "Person",
                            "name": "Mezz Mezzrow",
                            "sort-name": "Mezzrow, Mezz"
                        }
                    },
                    " & ",
                    {
                        "artist": {
                            "id": "81e26fc9-ddb5-42cf-9b31-2e0f55bf6342",
                            "type": "Person",
                            "name": "Pee Wee Russell",
                            "sort-name": "Russell, Pee Wee"
                        }
                    }
                ],
                "date": "2005-08-29",
                "country": "DE",
                "release-event-list": [
                    {
                        "date": "2005-08-29",
                        "area": {
                            "id": "85752fda-13c4-31a3-bee5-0e5cb1f51dad",
                            "name": "Germany",
                            "sort-name": "Germany",
                            "iso-3166-1-code-list": [
                                "DE"
                            ]
                        }
                    }
                ],
                "release-event-count": 1,
                "barcode": "4011222228000",
                "medium-list": [
                    {
                        "title": "Sidney Bechet",
                        "position": "1",
                        "format": "CD",
                        "disc-list": [
                            {
                                "id": "p973wu1f8RhazI_7g_cpVam4IrQ-",
                                "sectors": "269301",
                                "offset-list": [
                                    150,
                                    14666,
                                    27364,
                                    41431,
                                    54564,
                                    70871,
                                    84484,
                                    97095,
                                    108355,
                                    121274,
                                    133758,
                                    148020,
                                    159121,
                                    169884,
                                    182978,
                                    195265,
                                    213816,
                                    228192,
                                    242545,
                                    255224
                                ],
                                "offset-count": 20
                            }
                        ],
                        "disc-count": 1,
                        "track-list": [
                            {
                                "id": "80447a51-f4ec-37b1-9337-6cdeeeb7e0a6",
                                "position": "4",
                                "number": "4",
                                "title": "Maple Leaf Rag",
                                "length": "175106",
                                "artist-credit": [
                                    {
                                        "artist": {
                                            "id": "bf1b23ea-9b76-42cf-a5f6-4a691e81af5e",
                                            "type": "Person",
                                            "name": "Sidney Bechet",
                                            "sort-name": "Bechet, Sidney"
                                        }
                                    }
                                ],
                                "artist-credit-phrase": "Sidney Bechet",
                                "track_or_recording_length": "175106"
                            }
                        ],
                        "track-count": 20
                    }
                ],
                "medium-count": 1,
                "artist-credit-phrase": "Sidney Bechet, Washboard Rhythm Kings, Mezz Mezzrow & Pee Wee Russell"
            },
            {
                "id": "eea9f32b-7d78-4565-aea2-10855472b998",
                "title": "Larkin's Jazz",
                "status": "Official",
                "quality": "normal",
                "text-representation": {
                    "language": "eng",
                    "script": "Latn"
                },
                "artist-credit": [
                    {
                        "artist": {
                            "id": "89ad4ac3-39f7-470e-963a-56509c546377",
                            "type": "Other",
                            "name": "Various Artists",
                            "sort-name": "Various Artists",
                            "disambiguation": "add compilations to this artist"
                        }
                    }
                ],
                "date": "2010-07-26",
                "country": "GB",
                "release-event-list": [
                    {
                        "date": "2010-07-26",
                        "area": {
                            "id": "8a754a16-0027-3a29-b6d7-2b40ea0481ed",
                            "name": "United Kingdom",
                            "sort-name": "United Kingdom",
                            "iso-3166-1-code-list": [
                                "GB"
                            ]
                        }
                    }
                ],
                "release-event-count": 1,
                "barcode": "805520021555",
                "medium-list": [
                    {
                        "title": "All What Jazz",
                        "position": "3",
                        "format": "CD",
                        "disc-list": [
                            {
                                "id": "G0HYykHzsB45_X8IZqcqEshg9r0-",
                                "sectors": "351788",
                                "offset-list": [
                                    150,
                                    13393,
                                    26575,
                                    39400,
                                    55307,
                                    74938,
                                    90718,
                                    104662,
                                    118964,
                                    133155,
                                    146404,
                                    163419,
                                    178886,
                                    193672,
                                    205893,
                                    222301,
                                    234044,
                                    250351,
                                    266318,
                                    281071,
                                    294246,
                                    309898,
                                    323488,
                                    338363
                                ],
                                "offset-count": 24
                            }
                        ],
                        "disc-count": 1,
                        "track-list": [
                            {
                                "id": "98cfb6e5-2095-3e74-a008-3c925faa45d6",
                                "position": "2",
                                "number": "2",
                                "title": "Maple Leaf Rag",
                                "length": "176000",
                                "artist-credit": [
                                    {
                                        "artist": {
                                            "id": "8ad3d3e1-0a20-4fe3-8c50-38293f62638d",
                                            "type": "Group",
                                            "name": "New Orleans Feetwarmers",
                                            "sort-name": "New Orleans Feetwarmers",
                                            "alias-list": [
                                                {
                                                    "sort-name": "The New Orleans Feetwarmers",
                                                    "alias": "The New Orleans Feetwarmers"
                                                }
                                            ],
                                            "alias-count": 1
                                        }
                                    }
                                ],
                                "artist-credit-phrase": "New Orleans Feetwarmers",
                                "track_or_recording_length": "176000"
                            }
                        ],
                        "track-count": 24
                    }
                ],
                "medium-count": 1,
                "artist-credit-phrase": "Various Artists"
            },
            {
                "id": "ba4befe1-c5e0-4b68-a308-ca553ebdf5a5",
                "title": "Simply Jazz Legends",
                "status": "Official",
                "quality": "normal",
                "text-representation": {
                    "language": "eng",
                    "script": "Latn"
                },
                "artist-credit": [
                    {
                        "artist": {
                            "id": "89ad4ac3-39f7-470e-963a-56509c546377",
                            "type": "Other",
                            "name": "Various Artists",
                            "sort-name": "Various Artists",
                            "disambiguation": "add compilations to this artist"
                        }
                    }
                ],
                "date": "2010",
                "country": "FR",
                "release-event-list": [
                    {
                        "date": "2010",
                        "area": {
                            "id": "08310658-51eb-3801-80de-5a0739207115",
                            "name": "France",
                            "sort-name": "France",
                            "iso-3166-1-code-list": [
                                "FR"
                            ]
                        }
                    }
                ],
                "release-event-count": 1,
                "medium-list": [
                    {
                        "position": "2",
                        "format": "CD",
                        "disc-list": [],
                        "disc-count": 0,
                        "track-list": [
                            {
                                "id": "f9e16cb0-59ab-383f-875e-489abaf41bb3",
                                "position": "16",
                                "number": "16",
                                "title": "Maple Leaf Rag",
                                "length": "176000",
                                "artist-credit": [
                                    {
                                        "artist": {
                                            "id": "bf1b23ea-9b76-42cf-a5f6-4a691e81af5e",
                                            "type": "Person",
                                            "name": "Sidney Bechet",
                                            "sort-name": "Bechet, Sidney"
                                        }
                                    }
                                ],
                                "artist-credit-phrase": "Sidney Bechet",
                                "track_or_recording_length": "176000"
                            }
                        ],
                        "track-count": 20
                    }
                ],
                "medium-count": 1,
                "artist-credit-phrase": "Various Artists"
            },
            {
                "id": "cfe54ee2-81b1-4942-b0f4-d977d8f15b29",
                "title": "Jazz: The Smithsonian Anthology",
                "status": "Official",
                "quality": "normal",
                "packaging": "Book",
                "text-representation": {
                    "language": "eng",
                    "script": "Latn"
                },
                "artist-credit": [
                    {
                        "artist": {
                            "id": "89ad4ac3-39f7-470e-963a-56509c546377",
                            "type": "Other",
                            "name": "Various Artists",
                            "sort-name": "Various Artists",
                            "disambiguation": "add compilations to this artist"
                        }
                    }
                ],
                "date": "2011-03-29",
                "country": "US",
                "release-event-list": [
                    {
                        "date": "2011-03-29",
                        "area": {
                            "id": "489ce91b-6658-3307-9877-795b68554c98",
                            "name": "United States",
                            "sort-name": "United States",
                            "iso-3166-1-code-list": [
                                "US"
                            ]
                        }
                    }
                ],
                "release-event-count": 1,
                "barcode": "093074082027",
                "medium-list": [
                    {
                        "position": "1",
                        "format": "CD",
                        "disc-list": [
                            {
                                "id": "UmEgAEleRmS_1NrKhpgW9.x14Ac-",
                                "sectors": "344633",
                                "offset-list": [
                                    150,
                                    11398,
                                    25171,
                                    39469,
                                    50639,
                                    65370,
                                    80078,
                                    93919,
                                    108972,
                                    123222,
                                    136957,
                                    152054,
                                    164479,
                                    180435,
                                    194524,
                                    209075,
                                    224516,
                                    235337,
                                    248795,
                                    263017,
                                    276072,
                                    289601,
                                    303917,
                                    316029,
                                    329941
                                ],
                                "offset-count": 25
                            }
                        ],
                        "disc-count": 1,
                        "track-list": [
                            {
                                "id": "594873ec-a76d-38d5-b5e5-83c5d135ae2e",
                                "position": "18",
                                "number": "18",
                                "title": "Maple Leaf Rag",
                                "length": "179000",
                                "artist-credit": [
                                    {
                                        "artist": {
                                            "id": "bf1b23ea-9b76-42cf-a5f6-4a691e81af5e",
                                            "type": "Person",
                                            "name": "Sidney Bechet",
                                            "sort-name": "Bechet, Sidney"
                                        }
                                    }
                                ],
                                "artist-credit-phrase": "Sidney Bechet",
                                "track_or_recording_length": "179000"
                            }
                        ],
                        "track-count": 25
                    }
                ],
                "medium-count": 1,
                "artist-credit-phrase": "Various Artists"
            },
            {
                "id": "d35ff2f5-cf28-43b8-8275-9c069d2ef27d",
                "title": "The Complete American Masters 1931-1953",
                "status": "Official",
                "quality": "normal",
                "packaging": "Other",
                "text-representation": {
                    "language": "eng",
                    "script": "Latn"
                },
                "artist-credit": [
                    {
                        "artist": {
                            "id": "bf1b23ea-9b76-42cf-a5f6-4a691e81af5e",
                            "type": "Person",
                            "name": "Sidney Bechet",
                            "sort-name": "Bechet, Sidney"
                        }
                    }
                ],
                "date": "2011-11-21",
                "country": "FR",
                "release-event-list": [
                    {
                        "date": "2011-11-21",
                        "area": {
                            "id": "08310658-51eb-3801-80de-5a0739207115",
                            "name": "France",
                            "sort-name": "France",
                            "iso-3166-1-code-list": [
                                "FR"
                            ]
                        }
                    }
                ],
                "release-event-count": 1,
                "barcode": "600753361672",
                "medium-list": [
                    {
                        "title": "1923-1932 Selected Recordings",
                        "position": "1",
                        "format": "CD",
                        "disc-list": [
                            {
                                "id": "G3EQ3s92kxiMbVXAOMyuPrZJ22U-",
                                "sectors": "334150",
                                "offset-list": [
                                    150,
                                    13694,
                                    27128,
                                    40472,
                                    54803,
                                    68373,
                                    82602,
                                    95966,
                                    109345,
                                    123954,
                                    136936,
                                    151161,
                                    166001,
                                    181331,
                                    194560,
                                    207228,
                                    222052,
                                    236904,
                                    250923,
                                    263748,
                                    277834,
                                    292299,
                                    306942,
                                    320150
                                ],
                                "offset-count": 24
                            }
                        ],
                        "disc-count": 1,
                        "track-list": [
                            {
                                "id": "b3ce2e33-7251-3eaf-8c6e-66ee5a644d31",
                                "position": "23",
                                "number": "23",
                                "title": "Maple Leaf Rag",
                                "length": "176106",
                                "artist-credit": [
                                    {
                                        "artist": {
                                            "id": "8ad3d3e1-0a20-4fe3-8c50-38293f62638d",
                                            "type": "Group",
                                            "name": "New Orleans Feetwarmers",
                                            "sort-name": "New Orleans Feetwarmers",
                                            "alias-list": [
                                                {
                                                    "sort-name": "The New Orleans Feetwarmers",
                                                    "alias": "The New Orleans Feetwarmers"
                                                }
                                            ],
                                            "alias-count": 1
                                        }
                                    }
                                ],
                                "artist-credit-phrase": "New Orleans Feetwarmers",
                                "track_or_recording_length": "176106"
                            }
                        ],
                        "track-count": 24
                    }
                ],
                "medium-count": 1,
                "artist-credit-phrase": "Sidney Bechet"
            },
            {
                "id": "261a409c-7d3c-45e9-904c-067e0960f514",
                "title": "New Orleans, New Orleans",
                "quality": "normal",
                "text-representation": {
                    "language": "eng",
                    "script": "Latn"
                },
                "artist-credit": [
                    {
                        "artist": {
                            "id": "89ad4ac3-39f7-470e-963a-56509c546377",
                            "type": "Other",
                            "name": "Various Artists",
                            "sort-name": "Various Artists",
                            "disambiguation": "add compilations to this artist"
                        }
                    }
                ],
                "medium-list": [
                    {
                        "position": "1",
                        "disc-list": [],
                        "disc-count": 0,
                        "track-list": [
                            {
                                "id": "a8345c67-2a97-3c42-a4b7-a5b38a72c109",
                                "position": "11",
                                "number": "11",
                                "title": "Maple Leaf Rag",
                                "length": "175000",
                                "artist-credit": [
                                    {
                                        "artist": {
                                            "id": "8ad3d3e1-0a20-4fe3-8c50-38293f62638d",
                                            "type": "Group",
                                            "name": "New Orleans Feetwarmers",
                                            "sort-name": "New Orleans Feetwarmers",
                                            "alias-list": [
                                                {
                                                    "sort-name": "The New Orleans Feetwarmers",
                                                    "alias": "The New Orleans Feetwarmers"
                                                }
                                            ],
                                            "alias-count": 1
                                        }
                                    }
                                ],
                                "artist-credit-phrase": "New Orleans Feetwarmers",
                                "track_or_recording_length": "175000"
                            }
                        ],
                        "track-count": 18
                    }
                ],
                "medium-count": 1,
                "artist-credit-phrase": "Various Artists"
            },
            {
                "id": "2faf6f08-01eb-4c95-8a45-62c332139d77",
                "title": "The Complete Sidney Bechet, Volumes 1/2 (1932\u20131941)",
                "status": "Official",
                "quality": "normal",
                "text-representation": {
                    "language": "eng",
                    "script": "Latn"
                },
                "artist-credit": [
                    {
                        "artist": {
                            "id": "bf1b23ea-9b76-42cf-a5f6-4a691e81af5e",
                            "type": "Person",
                            "name": "Sidney Bechet",
                            "sort-name": "Bechet, Sidney"
                        }
                    }
                ],
                "medium-list": [
                    {
                        "position": "1",
                        "disc-list": [],
                        "disc-count": 0,
                        "track-list": [
                            {
                                "id": "3c986109-bbac-3ef5-9262-6736c5702662",
                                "position": "5",
                                "number": "5",
                                "title": "Maple Leaf Rag",
                                "length": "175200",
                                "artist-credit": [
                                    {
                                        "artist": {
                                            "id": "bf1b23ea-9b76-42cf-a5f6-4a691e81af5e",
                                            "type": "Person",
                                            "name": "Sidney Bechet",
                                            "sort-name": "Bechet, Sidney"
                                        }
                                    }
                                ],
                                "artist-credit-phrase": "Sidney Bechet",
                                "track_or_recording_length": "175200"
                            }
                        ],
                        "track-count": 17
                    }
                ],
                "medium-count": 1,
                "artist-credit-phrase": "Sidney Bechet"
            },
            {
                "id": "02d19dd7-45db-44bc-9eee-235b75db72a1",
                "title": "When the Sun Sets Down South",
                "status": "Official",
                "quality": "normal",
                "text-representation": {
                    "language": "eng",
                    "script": "Latn"
                },
                "artist-credit": [
                    {
                        "artist": {
                            "id": "bf1b23ea-9b76-42cf-a5f6-4a691e81af5e",
                            "type": "Person",
                            "name": "Sidney Bechet",
                            "sort-name": "Bechet, Sidney"
                        }
                    }
                ],
                "country": "DE",
                "release-event-list": [
                    {
                        "area": {
                            "id": "85752fda-13c4-31a3-bee5-0e5cb1f51dad",
                            "name": "Germany",
                            "sort-name": "Germany",
                            "iso-3166-1-code-list": [
                                "DE"
                            ]
                        }
                    }
                ],
                "release-event-count": 1,
                "barcode": "4029758936122",
                "medium-list": [
                    {
                        "position": "1",
                        "format": "CD",
                        "disc-list": [
                            {
                                "id": "JOX2o3KScl7EsmSUwg2PRVYjR_o-",
                                "sectors": "319712",
                                "offset-list": [
                                    150,
                                    13766,
                                    28385,
                                    39963,
                                    53736,
                                    66888,
                                    81149,
                                    92203,
                                    108609,
                                    127072,
                                    146170,
                                    164816,
                                    178483,
                                    192624,
                                    205885,
                                    219535,
                                    229434,
                                    238200,
                                    251930,
                                    264190,
                                    278506,
                                    292056
                                ],
                                "offset-count": 22
                            }
                        ],
                        "disc-count": 1,
                        "track-list": [
                            {
                                "id": "1010b8f1-3b8a-3170-a53e-0e3dd0372c86",
                                "position": "5",
                                "number": "5",
                                "title": "Maple Leaf Rag",
                                "length": "175000",
                                "artist-credit": [
                                    {
                                        "artist": {
                                            "id": "bf1b23ea-9b76-42cf-a5f6-4a691e81af5e",
                                            "type": "Person",
                                            "name": "Sidney Bechet",
                                            "sort-name": "Bechet, Sidney"
                                        }
                                    }
                                ],
                                "artist-credit-phrase": "Sidney Bechet",
                                "track_or_recording_length": "175000"
                            }
                        ],
                        "track-count": 22
                    }
                ],
                "medium-count": 1,
                "artist-credit-phrase": "Sidney Bechet"
            }
        ],
        "release-count": 19,
        "isrc-list": [
            "USBB10000282",
            "USBJN0920018"
        ],
        "isrc-count": 2,
        "artist-relation-list": [
            {
                "type": "instrument",
                "type-id": "59054b12-01ac-43ee-a618-285fd397e461",
                "target": "bf1b23ea-9b76-42cf-a5f6-4a691e81af5e",
                "direction": "backward",
                "begin": "1932-09-15",
                "end": "1932-09-15",
                "ended": "true",
                "attribute-list": [
                    "soprano saxophone"
                ],
                "artist": {
                    "id": "bf1b23ea-9b76-42cf-a5f6-4a691e81af5e",
                    "type": "Person",
                    "name": "Sidney Bechet",
                    "sort-name": "Bechet, Sidney"
                },
                "attributes": [
                    {
                        "type-id": "4a32d2f2-2ac7-423d-9820-2c0b7ff37f60",
                        "attribute": "soprano saxophone"
                    }
                ]
            },
            {
                "type": "instrument",
                "type-id": "59054b12-01ac-43ee-a618-285fd397e461",
                "target": "77008e19-39fc-44f2-ba9a-8b548b804d5d",
                "direction": "backward",
                "begin": "1932-09-15",
                "end": "1932-09-15",
                "ended": "true",
                "attribute-list": [
                    "piano"
                ],
                "artist": {
                    "id": "77008e19-39fc-44f2-ba9a-8b548b804d5d",
                    "type": "Person",
                    "name": "Hank Duncan",
                    "sort-name": "Duncan, Hank"
                },
                "attributes": [
                    {
                        "type-id": "b3eac5f9-7859-4416-ac39-7154e2e8d348",
                        "attribute": "piano"
                    }
                ]
            },
            {
                "type": "instrument",
                "type-id": "59054b12-01ac-43ee-a618-285fd397e461",
                "target": "04ce08d7-1f21-4ada-90b3-3089554b9b3d",
                "direction": "backward",
                "begin": "1932-09-15",
                "end": "1932-09-15",
                "ended": "true",
                "attribute-list": [
                    "trumpet"
                ],
                "artist": {
                    "id": "04ce08d7-1f21-4ada-90b3-3089554b9b3d",
                    "type": "Person",
                    "name": "Tommy Ladnier",
                    "sort-name": "Ladnier, Tommy",
                    "disambiguation": "American jazz trumpeter"
                },
                "attributes": [
                    {
                        "type-id": "1c8f9780-2f16-4891-b66d-bb7aa0820dbd",
                        "attribute": "trumpet"
                    }
                ]
            },
            {
                "type": "instrument",
                "type-id": "59054b12-01ac-43ee-a618-285fd397e461",
                "target": "ce9e4e60-a346-4c70-8a83-3768c5e357e2",
                "direction": "backward",
                "begin": "1932-09-15",
                "end": "1932-09-15",
                "ended": "true",
                "attribute-list": [
                    "drums (drum set)"
                ],
                "artist": {
                    "id": "ce9e4e60-a346-4c70-8a83-3768c5e357e2",
                    "type": "Person",
                    "name": "Morris Morand",
                    "sort-name": "Morand, Morris"
                },
                "attributes": [
                    {
                        "type-id": "12092505-6ee1-46af-a15a-b5b468b6b155",
                        "attribute": "drums (drum set)"
                    }
                ]
            },
            {
                "type": "instrument",
                "type-id": "59054b12-01ac-43ee-a618-285fd397e461",
                "target": "72645c3e-285b-4bab-921d-8664f8c4697d",
                "direction": "backward",
                "begin": "1932-09-15",
                "end": "1932-09-15",
                "ended": "true",
                "attribute-list": [
                    "double bass"
                ],
                "artist": {
                    "id": "72645c3e-285b-4bab-921d-8664f8c4697d",
                    "type": "Person",
                    "name": "Wilson Myers",
                    "sort-name": "Myers, Wilson"
                },
                "attributes": [
                    {
                        "type-id": "7bd32b95-416f-4244-a98b-1311ec69c7db",
                        "credited-as": "bass",
                        "attribute": "double bass"
                    }
                ]
            },
            {
                "type": "instrument",
                "type-id": "59054b12-01ac-43ee-a618-285fd397e461",
                "target": "9ddc93e5-66a5-4f86-886b-767628cc09b4",
                "direction": "backward",
                "begin": "1932-09-15",
                "end": "1932-09-15",
                "ended": "true",
                "attribute-list": [
                    "trombone"
                ],
                "artist": {
                    "id": "9ddc93e5-66a5-4f86-886b-767628cc09b4",
                    "type": "Person",
                    "name": "Teddy Nixon",
                    "sort-name": "Nixon, Teddy"
                },
                "attributes": [
                    {
                        "type-id": "f6100277-c7b8-4c8d-aa26-d8cd014b6761",
                        "attribute": "trombone"
                    }
                ]
            }
        ],
        "work-relation-list": [
            {
                "type": "performance",
                "type-id": "a3005666-a872-32c3-ad06-98af558e99b0",
                "target": "a28705df-3bfa-3888-b3e9-cc707bda74dc",
                "direction": "forward",
                "begin": "1932-09-15",
                "end": "1932-09-15",
                "ended": "true",
                "work": {
                    "id": "a28705df-3bfa-3888-b3e9-cc707bda74dc",
                    "title": "Maple Leaf Rag",
                    "language": "zxx",
                    "disambiguation": "piano rag",
                    "artist-relation-list": [
                        {
                            "type": "composer",
                            "type-id": "d59d99ea-23d4-4a80-b066-edca32ee158f",
                            "target": "aec8a328-d2e8-4780-b2ea-318c7f8d6f75",
                            "direction": "backward",
                            "begin": "1899",
                            "end": "1899",
                            "ended": "true",
                            "artist": {
                                "id": "aec8a328-d2e8-4780-b2ea-318c7f8d6f75",
                                "type": "Person",
                                "name": "Scott Joplin",
                                "sort-name": "Joplin, Scott",
                                "disambiguation": "composer and pianist"
                            }
                        }
                    ],
                    "url-relation-list": [
                        {
                            "type": "download for free",
                            "type-id": "0cc8527e-ea40-40dd-b144-3b7588e759bf",
                            "target": "https://imslp.org/wiki/Maple_Leaf_Rag_(Joplin,_Scott)",
                            "direction": "backward"
                        },
                        {
                            "type": "wikidata",
                            "type-id": "587fdd8f-080e-46a9-97af-6425ebbcb3a2",
                            "target": "https://www.wikidata.org/wiki/Q277463",
                            "direction": "backward"
                        }
                    ],
                    "work-relation-list": [
                        {
                            "type": "arrangement",
                            "type-id": "51975ed8-bbfa-486b-9f28-5947f4370299",
                            "target": "16bcc998-53fa-4120-972c-4616ac2c49a0",
                            "direction": "forward",
                            "work": {
                                "id": "16bcc998-53fa-4120-972c-4616ac2c49a0",
                                "type": "Song",
                                "title": "Maple Leaf Rag",
                                "disambiguation": "catch-all for arrangements"
                            }
                        },
                        {
                            "type": "other version",
                            "type-id": "7440b539-19ab-4243-8c03-4f5942ca2218",
                            "target": "aae2e33c-b851-4279-a92e-35099c31e82c",
                            "direction": "forward",
                            "work": {
                                "id": "aae2e33c-b851-4279-a92e-35099c31e82c",
                                "title": "Maple Leaf Rag",
                                "disambiguation": "song"
                            }
                        }
                    ]
                }
            }
        ],
        "artist-credit-phrase": "New Orleans Feetwarmers"
    }
}