{
    "recording": {
        "id": "080a5a42-6260-4a73-b08c-768df63201bc",
        "title": "Tricotism",
        "length": "277000",
        "artist-credit": [
            {
                "artist": {
                    "id": "5ecae9f0-fb95-455e-847d-0cbb3b85a976",
                    "type": "Group",
                    "name": "Lucky Thompson Trio",
                    "sort-name": "Thompson, Lucky, Trio",
                    "tag-list": [
                        {
                            "count": "1",
                            "name": "jazz"
                        }
                    ]
                }
            }
        ],
        "release-list": [
            {
                "id": "cfe54ee2-81b1-4942-b0f4-d977d8f15b29",
                "title": "Jazz: The Smithsonian Anthology",
                "status": "Official",
                "quality": "normal",
                "packaging": "Book",
                "text-representation": {
                    "language": "eng",
                    "script": "Latn"
                },
                "artist-credit": [
                    {
                        "artist": {
                            "id": "89ad4ac3-39f7-470e-963a-56509c546377",
                            "type": "Other",
                            "name": "Various Artists",
                            "sort-name": "Various Artists",
                            "disambiguation": "add compilations to this artist"
                        }
                    }
                ],
                "date": "2011-03-29",
                "country": "US",
                "release-event-list": [
                    {
                        "date": "2011-03-29",
                        "area": {
                            "id": "489ce91b-6658-3307-9877-795b68554c98",
                            "name": "United States",
                            "sort-name": "United States",
                            "iso-3166-1-code-list": [
                                "US"
                            ]
                        }
                    }
                ],
                "release-event-count": 1,
                "barcode": "093074082027",
                "medium-list": [
                    {
                        "position": "3",
                        "format": "CD",
                        "disc-list": [
                            {
                                "id": "6bYTEmWOqKg8Uc6_mqHw76wUElU-",
                                "sectors": "350639",
                                "offset-list": [
                                    150,
                                    13853,
                                    25106,
                                    38989,
                                    53588,
                                    68025,
                                    86435,
                                    118305,
                                    137804,
                                    157589,
                                    168171,
                                    188931,
                                    219574,
                                    243192,
                                    259285,
                                    282972,
                                    323867,
                                    335767
                                ],
                                "offset-count": 18
                            }
                        ],
                        "disc-count": 1,
                        "track-list": [
                            {
                                "id": "cec4a659-4779-33d6-80c7-f3ca289de089",
                                "position": "11",
                                "number": "11",
                                "title": "Tricotism",
                                "length": "277000",
                                "artist-credit": [
                                    {
                                        "artist": {
                                            "id": "5ecae9f0-fb95-455e-847d-0cbb3b85a976",
                                            "type": "Group",
                                            "name": "Lucky Thompson Trio",
                                            "sort-name": "Thompson, Lucky, Trio",
                                            "tag-list": [
                                                {
                                                    "count": "1",
                                                    "name": "jazz"
                                                }
                                            ]
                                        }
                                    }
                                ],
                                "artist-credit-phrase": "Lucky Thompson Trio",
                                "track_or_recording_length": "277000"
                            }
                        ],
                        "track-count": 18
                    }
                ],
                "medium-count": 1,
                "artist-credit-phrase": "Various Artists"
            }
        ],
        "release-count": 1,
        "isrc-list": [
            "USBJN0920060"
        ],
        "isrc-count": 1,
        "artist-relation-list": [
            {
                "type": "instrument",
                "type-id": "59054b12-01ac-43ee-a618-285fd397e461",
                "target": "0b65e7ab-6437-4792-82da-7bfb74f72966",
                "direction": "backward",
                "begin": "1956-01-24",
                "end": "1956-01-24",
                "ended": "true",
                "attribute-list": [
                    "guitar"
                ],
                "artist": {
                    "id": "0b65e7ab-6437-4792-82da-7bfb74f72966",
                    "type": "Person",
                    "name": "Skeeter Best",
                    "sort-name": "Best, Skeeter"
                },
                "attributes": [
                    {
                        "type-id": "63021302-86cd-4aee-80df-2270d54f4978",
                        "attribute": "guitar"
                    }
                ]
            },
            {
                "type": "instrument",
                "type-id": "59054b12-01ac-43ee-a618-285fd397e461",
                "target": "28f6d494-d44b-4bd3-aed9-1d4909875ca1",
                "direction": "backward",
                "begin": "1956-01-24",
                "end": "1956-01-24",
                "ended": "true",
                "attribute-list": [
                    "double bass"
                ],
                "artist": {
                    "id": "28f6d494-d44b-4bd3-aed9-1d4909875ca1",
                    "type": "Person",
                    "name": "Oscar Pettiford",
                    "sort-name": "Pettiford, Oscar"
                },
                "attributes": [
                    {
                        "type-id": "7bd32b95-416f-4244-a98b-1311ec69c7db",
                        "attribute": "double bass"
                    }
                ]
            },
            {
                "type": "instrument",
                "type-id": "59054b12-01ac-43ee-a618-285fd397e461",
                "target": "4b0b1bd5-35e8-4764-b4f2-55ef56f595aa",
                "direction": "backward",
                "begin": "1956-01-24",
                "end": "1956-01-24",
                "ended": "true",
                "attribute-list": [
                    "tenor saxophone"
                ],
                "artist": {
                    "id": "4b0b1bd5-35e8-4764-b4f2-55ef56f595aa",
                    "type": "Person",
                    "name": "Lucky Thompson",
                    "sort-name": "Thompson, Lucky"
                },
                "attributes": [
                    {
                        "type-id": "ef7382cf-d5b4-4923-8b9e-3c482ed84b5e",
                        "attribute": "tenor saxophone"
                    }
                ]
            }
        ],
        "work-relation-list": [
            {
                "type": "performance",
                "type-id": "a3005666-a872-32c3-ad06-98af558e99b0",
                "target": "c0487132-4850-44c7-aa69-e0240248e40e",
                "direction": "forward",
                "begin": "1956-01-24",
                "end": "1956-01-24",
                "ended": "true",
                "work": {
                    "id": "c0487132-4850-44c7-aa69-e0240248e40e",
                    "type": "Song",
                    "title": "Tricotism",
                    "language": "zxx",
                    "artist-relation-list": [
                        {
                            "type": "composer",
                            "type-id": "d59d99ea-23d4-4a80-b066-edca32ee158f",
                            "target": "28f6d494-d44b-4bd3-aed9-1d4909875ca1",
                            "direction": "backward",
                            "artist": {
                                "id": "28f6d494-d44b-4bd3-aed9-1d4909875ca1",
                                "type": "Person",
                                "name": "Oscar Pettiford",
                                "sort-name": "Pettiford, Oscar"
                            }
                        }
                    ]
                }
            }
        ],
        "artist-credit-phrase": "Lucky Thompson Trio"
    }
}